zeroq-0.1.0.dist-info/METADATA
zeroq-0.1.0.dist-info/WHEEL
zeroq-0.1.0.dist-info/licenses/LICENSE
zeroq.libs/libgcc_s-5b5488a6.so.1
zeroq/__init__.py
zeroq/py.typed
zeroq/zeroq.pyi
zeroq/zeroq.pypy39-pp73-arm-linux-gnu.so
zeroq-0.1.0.dist-info/RECORD
