Metadata-Version: 2.4
Name: zeroq
Version: 0.1.0
Classifier: Development Status :: 4 - Beta
Classifier: Intended Audience :: Developers
Classifier: License :: OSI Approved :: MIT License
Classifier: Programming Language :: Python :: 3
Classifier: Programming Language :: Rust
Classifier: Topic :: Software Development :: Libraries
Classifier: Topic :: System :: Distributed Computing
License-File: LICENSE
Summary: High-performance shared memory queue for Python (Rust-powered)
Keywords: queue,shared memory,ipc,rust,pyo3,fast,mpmc
Author-email: Ivan Kosilov <idkosilov@gmail.com>
License: MIT
Requires-Python: >=3.9
